pandas_nested_dicts/__init__.py
pandas_nested_dicts/dict_conversion.py
tests/__init__.py
tests/test_dict_conversion.py
pandas_nested_dicts-0.0.1.dist-info/LICENSE
pandas_nested_dicts-0.0.1.dist-info/METADATA
pandas_nested_dicts-0.0.1.dist-info/WHEEL
pandas_nested_dicts-0.0.1.dist-info/top_level.txt
pandas_nested_dicts-0.0.1.dist-info/RECORD
